prajil/__init__.py
prajil/numberprograms.py
prajil-0.0.20.dist-info/METADATA
prajil-0.0.20.dist-info/WHEEL
prajil-0.0.20.dist-info/licenses/LICENSE.txt
prajil-0.0.20.dist-info/RECORD
