Metadata-Version: 2.1
Name: prajil
Version: 0.0.20
Summary: this project helps us to calculate square root ,cube root, emrip number,prime number etc
Project-URL: Homepage, https://github.com/pypa/sampleproject
Project-URL: Bug Tracker, https://github.com/pypa/sampleproject/issues
Author-email: prajil <prajiltpriyan@example.com>
License-File: LICENSE.txt
Classifier: License :: OSI Approved :: MIT License
Classifier: Operating System :: OS Independent
Classifier: Programming Language :: Python :: 3
Requires-Python: >=3.7
